tno/mpc/protocols/distributed_keygen/__init__.py
tno/mpc/protocols/distributed_keygen/distributed_keygen.py
tno/mpc/protocols/distributed_keygen/paillier_shared_key.py
tno/mpc/protocols/distributed_keygen/py.typed
tno/mpc/protocols/distributed_keygen/utils.py
tno/mpc/protocols/distributed_keygen/test/__init__.py
tno/mpc/protocols/distributed_keygen/test/conftest.py
tno/mpc/protocols/distributed_keygen/test/test_distributed_keygen.py
tno/mpc/protocols/distributed_keygen/test/test_serialization.py
tno/mpc/protocols/distributed_keygen/test/test_data/distributed_key_threshold_0_3parties_0.obj
tno/mpc/protocols/distributed_keygen/test/test_data/distributed_key_threshold_0_3parties_1.obj
tno/mpc/protocols/distributed_keygen/test/test_data/distributed_key_threshold_0_3parties_2.obj
tno/mpc/protocols/distributed_keygen/test/test_data/distributed_key_threshold_0_4parties_0.obj
tno/mpc/protocols/distributed_keygen/test/test_data/distributed_key_threshold_0_4parties_1.obj
tno/mpc/protocols/distributed_keygen/test/test_data/distributed_key_threshold_0_4parties_2.obj
tno/mpc/protocols/distributed_keygen/test/test_data/distributed_key_threshold_0_4parties_3.obj
tno/mpc/protocols/distributed_keygen/test/test_data/distributed_key_threshold_0_5parties_0.obj
tno/mpc/protocols/distributed_keygen/test/test_data/distributed_key_threshold_0_5parties_1.obj
tno/mpc/protocols/distributed_keygen/test/test_data/distributed_key_threshold_0_5parties_2.obj
tno/mpc/protocols/distributed_keygen/test/test_data/distributed_key_threshold_0_5parties_3.obj
tno/mpc/protocols/distributed_keygen/test/test_data/distributed_key_threshold_0_5parties_4.obj
tno/mpc/protocols/distributed_keygen/test/test_data/distributed_key_threshold_1_3parties_0.obj
tno/mpc/protocols/distributed_keygen/test/test_data/distributed_key_threshold_1_3parties_1.obj
tno/mpc/protocols/distributed_keygen/test/test_data/distributed_key_threshold_1_3parties_2.obj
tno.mpc.protocols.distributed_keygen-4.3.0.dist-info/LICENSE
tno.mpc.protocols.distributed_keygen-4.3.0.dist-info/METADATA
tno.mpc.protocols.distributed_keygen-4.3.0.dist-info/WHEEL
tno.mpc.protocols.distributed_keygen-4.3.0.dist-info/top_level.txt
tno.mpc.protocols.distributed_keygen-4.3.0.dist-info/RECORD
