Metadata-Version: 2.1
Name: tno.mpc.protocols.distributed_keygen
Version: 4.3.0
Summary: Distributed key generation using Paillier homomorphic encryption
Author-email: TNO PET Lab <petlab@tno.nl>
Maintainer-email: TNO PET Lab <petlab@tno.nl>
License: Apache License, Version 2.0
Project-URL: Homepage, https://pet.tno.nl/
Project-URL: Documentation, https://docs.pet.tno.nl/mpc/protocols/distributed_keygen/4.3.0
Project-URL: Source, https://github.com/TNO-MPC/protocols.distributed_keygen
Keywords: TNO,MPC,multi-party computation,encryption schemes,distributed,paillier,cryptosystem,protocols
Platform: any
Classifier: License :: OSI Approved :: Apache Software License
Classifier: Programming Language :: Python :: 3
Classifier: Operating System :: OS Independent
Classifier: Intended Audience :: Developers
Classifier: Intended Audience :: Information Technology
Classifier: Intended Audience :: Science/Research
Classifier: Typing :: Typed
Classifier: Topic :: Security :: Cryptography
Requires-Python: >=3.9
License-File: LICENSE
Requires-Dist: sympy
Requires-Dist: tno.mpc.communication~=4.8
Requires-Dist: tno.mpc.encryption_schemes.paillier>=3.0.1,~=3.0
Requires-Dist: tno.mpc.encryption_schemes.shamir<2.0,>=1.3.0
Requires-Dist: tno.mpc.encryption_schemes.utils~=0.10
Requires-Dist: typing_extensions; python_version < "3.12"
Provides-Extra: gmpy
Requires-Dist: tno.mpc.encryption_schemes.paillier[gmpy]; extra == "gmpy"
Requires-Dist: tno.mpc.encryption_schemes.shamir[gmpy]; extra == "gmpy"
Requires-Dist: tno.mpc.encryption_schemes.utils[gmpy]; extra == "gmpy"
Provides-Extra: tests
Requires-Dist: pytest; extra == "tests"
Requires-Dist: pytest-asyncio>=0.17; extra == "tests"
Provides-Extra: bench
Requires-Dist: numpy; extra == "bench"
Requires-Dist: matplotlib; extra == "bench"
Requires-Dist: pandas; extra == "bench"
Requires-Dist: seaborn; extra == "bench"
Requires-Dist: tqdm; extra == "bench"
Requires-Dist: tikzplotlib; extra == "bench"
